nicelib/__about__.py
nicelib/__init__.py
nicelib/build.py
nicelib/nicelib.py
nicelib/platform.py
nicelib/process.py
nicelib/util.py
nicelib/parser/__init__.py
nicelib/parser/_build_tables.py
nicelib/parser/cpp_generator.py
nicelib/parser/cpp_lexer.py
nicelib/parser/cpp_parser.py
NiceLib-0.7.1.dist-info/LICENSE
NiceLib-0.7.1.dist-info/METADATA
NiceLib-0.7.1.dist-info/WHEEL
NiceLib-0.7.1.dist-info/top_level.txt
NiceLib-0.7.1.dist-info/RECORD
