Metadata-Version: 2.1
Name: NiceLib
Version: 0.7.1
Summary: A package for rapidly developing "nice" Python bindings to C libraries, using `cffi`
Home-page: https://github.com/mabuchilab/NiceLib
Author: Nate Bogdanowicz
Author-email: natezb@gmail.com
License: GPLv3
Platform: UNKNOWN
Classifier: License :: OSI Approved :: GNU General Public License v3 (GPLv3)
Classifier: Programming Language :: Python :: 2
Classifier: Programming Language :: Python :: 2.7
Classifier: Programming Language :: Python :: 3
Classifier: Programming Language :: Python :: 3.4
Classifier: Programming Language :: Python :: 3.5
Classifier: Programming Language :: Python :: 3.6
License-File: LICENSE
Requires-Dist: cffi (>=1.5)
Requires-Dist: pycparser
Requires-Dist: future
Requires-Dist: chainmap (>=1.0.2) ; python_version < "3.3"
Requires-Dist: enum34 (>=1.0.4) ; python_version < "3.4"
